<annotation>
	<folder>Mouse</folder>
	<filename>63a73f12c8034c0da56107f41f4496a0.jpg</filename>
	<path>C:\Users\Indra\JupyterNotebook\dataset iki\percobaan 2\Mouse\63a73f12c8034c0da56107f41f4496a0.jpg</path>
	<source>
		<database>Unknown</database>
	</source>
	<size>
		<width>643</width>
		<height>643</height>
		<depth>3</depth>
	</size>
	<segmented>0</segmented>
	<object>
		<name>Mouse</name>
		<pose>Unspecified</pose>
		<truncated>0</truncated>
		<difficult>0</difficult>
		<bndbox>
			<xmin>146</xmin>
			<ymin>27</ymin>
			<xmax>495</xmax>
			<ymax>632</ymax>
		</bndbox>
	</object>
</annotation>
