<annotation>
	<folder>Kamera</folder>
	<filename>770d375d6929445fa209075bfd8542cc.jpg</filename>
	<path>C:\Users\Indra\JupyterNotebook\dataset iki\percobaan 2\Kamera\770d375d6929445fa209075bfd8542cc.jpg</path>
	<source>
		<database>Unknown</database>
	</source>
	<size>
		<width>1024</width>
		<height>833</height>
		<depth>3</depth>
	</size>
	<segmented>0</segmented>
	<object>
		<name>kamera</name>
		<pose>Unspecified</pose>
		<truncated>0</truncated>
		<difficult>0</difficult>
		<bndbox>
			<xmin>9</xmin>
			<ymin>5</ymin>
			<xmax>1009</xmax>
			<ymax>822</ymax>
		</bndbox>
	</object>
</annotation>
